.gitignore
MANIFEST.in
README.md
claude.yaml
package.json
pyproject.toml
setup.py
tsconfig.json
webpack.config.js
bin/start-claude-server
claude/__init__.py
claude/api.py
claude/app.py
claude/chromecast_proxy_service.py
claude/config.py
claude/config_sync_service.py
claude/controller_base.py
claude/controller_cache.py
claude/javascript_libraries.py
claude/memcache.py
claude/tools.py
claude/transmission.py
claude.egg-info/PKG-INFO
claude.egg-info/SOURCES.txt
claude.egg-info/dependency_links.txt
claude.egg-info/requires.txt
claude.egg-info/top_level.txt
claude/static/bundle.js
claude/static/bundle.js.map
claude/static/fonts/digital7.otf
claude/static/fonts/hfutura2.otf
claude/static/pics/canvas_blue_texture_surface_shadow_44965_1920x1200.jpg
claude/static/pics/localhost.png
claude/static/pics/private.png
claude/static/pics/rings.svg
claude/templates/index.html
ts/ConfigSyncService.ts
ts/actions.ts
ts/api.ts
ts/index.tsx
ts/layoutConfig.ts
ts/locales.ts
ts/reducers.ts
ts/store.ts
ts/themes.ts
ts/tools.ts
ts/types.ts
ts/widgetRegistry.ts
ts/components/CalendarWidget.tsx
ts/components/ChromecastWidget.tsx
ts/components/ClockWidget.tsx
ts/components/Dashboard.tsx
ts/components/DashboardConfigDialog.tsx
ts/components/FlagIcon.tsx
ts/components/IdokepCurrent.tsx
ts/components/IdokepDays.tsx
ts/components/IdokepHours.tsx
ts/components/InfluxTable.tsx
ts/components/ServerStatusWidget.tsx
ts/components/StorageStatusWidget.tsx
ts/components/TransmissionWidget.tsx
ts/components/WidgetBoilerplate.tsx
ts/components/WidgetFrame.tsx
ts/components/WidgetMenu.tsx
ts/components/WidgetSettingsDialog.tsx
ts/components/tools.tsx
ts/containers/AddWidgetMenu.tsx
ts/containers/App.tsx
ts/containers/ControlBar.tsx
ts/containers/DashboardSelector.tsx
ts/containers/DashboardSettingsButton.tsx
ts/containers/WidgetFrame.ts