Metadata-Version: 1.0
Name: claude
Version: 0.4.6
Summary: Pluginable dashboard app
Home-page: https://github.com/voidpp/claude
Author: Lajos Santa
Author-email: santa.lajos@gmail.com
License: MIT
Platform: UNKNOWN
